CHANGELOG.txt
LICENSE.txt
MANIFEST.in
README.txt
setup.py
.ipynb_checkpoints/CHANGELOG-checkpoint.txt
.ipynb_checkpoints/LICENSE-checkpoint.txt
.ipynb_checkpoints/README-checkpoint.txt
.ipynb_checkpoints/setup-checkpoint.py
cobrospsg/__init__.py
cobrospsg.egg-info/PKG-INFO
cobrospsg.egg-info/SOURCES.txt
cobrospsg.egg-info/dependency_links.txt
cobrospsg.egg-info/top_level.txt
cobrospsg/.ipynb_checkpoints/__init__-checkpoint.py