Metadata-Version: 1.1
Name: cobrospsg
Version: 0.0.8
Summary: Paquete con funciones para modelos predictivos de Cobros de Prosegur
Home-page: UNKNOWN
Author: Martin Ehman
Author-email: martinehman90@gmail.com
License: MIT
Keywords: aws,prosegur
Platform: UNKNOWN
Classifier: License :: OSI Approved :: MIT License
Classifier: Programming Language :: Python :: 3
